docklift/__init__.py
docklift/bootstrap.py
docklift/cli.py
docklift/config.py
docklift/connection.py
docklift/deploy.py
docklift-0.1.0.dist-info/METADATA
docklift-0.1.0.dist-info/WHEEL
docklift-0.1.0.dist-info/entry_points.txt
docklift-0.1.0.dist-info/RECORD
