Metadata-Version: 2.4
Name: docklift
Version: 0.1.0
Summary: Deploy web applications to VPS using Docker Compose with automatic SSL
Author-email: Amir Karimi <me@amirkarimi.dev>
Requires-Python: >=3.12
Requires-Dist: click>=8.1.7
Requires-Dist: fabric>=3.2.2
Requires-Dist: pydantic>=2.5.0
Requires-Dist: pyyaml>=6.0.1
Requires-Dist: rich>=13.7.0
